FutureWiz_Daily_Verilog_Codes/revision_verilog_codes_july/rev01_df_fa/design.v
//dataflow code for full adder 
module df_full_adder(input a,b,c, output sum,cout);
	assign sum = a ^ b ^ c;
	assign cout = (a & b ) | (b & c) | (c & a);
endmodule

FutureWiz_Daily_Verilog_Codes/revision_verilog_codes_july/rev01_df_fa/testbench.v
`timescale 1ns/1ps
module df_fa_test;
	reg a,b,c;
	wire sum, cout;
	df_full_adder dut(.a(a),.b(b),.c(c),.sum(sum),.cout(cout));
	
	//assign the testing values
	initial begin
	
	$dumpfile("wave.vcd"); //dumpfile to store the output values
	$dumpvars(0,df_fa_test);
	
	a = 0; b = 0 ; c = 0; #2; //values are given after delay of 2 ns
	a = 0; b = 0 ; c = 1; #2;
	a = 0; b = 1 ; c = 0; #2;
	a = 0; b = 1 ; c = 1; #2;
	a = 1; b = 0 ; c = 0; #2;
	a = 1; b = 0 ; c = 1; #2;
	a = 1; b = 1 ; c = 0; #2;
	a = 1; b = 1 ; c = 1; #2;
	$finish ;
	end
	//viewing the values 
	initial begin
	$monitor ("Simtime : [%0t] value of a = %0b, b = %0b, c = %0b, sum = %0b , carry_out = %0b ",$time,a,b,c,sum,cout);
	end
	
endmodule
	
	
	/*Clock Generation
Latches and FFs !!!!
Combinational Circuits with all modeling Styles !!!!*/

FutureWiz_Daily_Verilog_Codes/revision_verilog_codes_july/rev01_df_fa/wave.vcd
$date
	Mon Jul  7 11:58:11 2025
$end
$version
	Icarus Verilog
$end
$timescale
	1ps
$end
$scope module df_fa_test $end
$var wire 1 ! sum $end
$var wire 1 " cout $end
$var reg 1 # a $end
$var reg 1 $ b $end
$var reg 1 % c $end
$scope module dut $end
$var wire 1 # a $end
$var wire 1 $ b $end
$var wire 1 % c $end
$var wire 1 " cout $end
$var wire 1 ! sum $end
$upscope $end
$upscope $end
$enddefinitions $end
$comment Show the parameter values. $end
$dumpall
$end
#0
$dumpvars
0%
0$
0#
0"
0!
$end
#2000
1!
1%
#4000
0%
1$
#6000
1"
0!
1%
#8000
0"
1!
0%
0$
1#
#10000
1"
0!
1%
#12000
0%
1$
#14000
1!
1%
