FutureWiz_Daily_Verilog_Codes/revision_verilog_codes_july/rev02_struct_fa_ha/half_add.v
module half_add(input a,b, output sum, carry);
	assign sum = a ^ b;
	assign carry = a & b;
endmodule

FutureWiz_Daily_Verilog_Codes/revision_verilog_codes_july/rev02_struct_fa_ha/design.v
`include "/home/amit_fesn/coding_verilog/struct_fa_ha/half_add.v"
module full_add(input a, b, cin, output sum, cout);
	wire sum1, carry1, carry2;
	//declare the instances of the 
	half_add ha1(.a(a),.b(b),.sum(sum1),.carry(carry1));
	half_add ha2(.a(sum1),.b(cin),.sum(sum),.carry(carry2));
	or o1(cout,carry2,carry1);
endmodule

FutureWiz_Daily_Verilog_Codes/revision_verilog_codes_july/rev02_struct_fa_ha/testbench.v
module fa_struct_test;
	reg a,b,cin;
	wire sum,carry;
	full_add fa1(a,b,cin,sum,cout);
	//generation of the stimulus 
	initial begin
		a = 0; b = 0; cin = 0;
	#2 cin = 1;
	#2 b = 1; cin = 0;
	#2 b = 0; cin = 1;
	#2 b = 1; cin = 1;	
	#2 a = 1; b = 0; cin = 0;
	#2 cin = 1;
	#2 b = 1; cin = 0;
	#2 b = 0; cin = 1;
	#2 b = 1; cin = 1;
	#10; $finish;
	end
	initial begin
	$dumpfile("wave.vcd");
	$dumpvars(0,fa_struct_test);
	end
endmodule

FutureWiz_Daily_Verilog_Codes/revision_verilog_codes_july/rev02_struct_fa_ha/wave.vcd
$date
	Tue Jul  8 17:37:36 2025
$end
$version
	Icarus Verilog
$end
$timescale
	1s
$end
$scope module fa_struct_test $end
$var wire 1 ! sum $end
$var wire 1 " cout $end
$var reg 1 # a $end
$var reg 1 $ b $end
$var reg 1 % cin $end
$scope module fa1 $end
$var wire 1 # a $end
$var wire 1 $ b $end
$var wire 1 % cin $end
$var wire 1 " cout $end
$var wire 1 & sum1 $end
$var wire 1 ! sum $end
$var wire 1 ' carry2 $end
$var wire 1 ( carry1 $end
$scope module ha1 $end
$var wire 1 # a $end
$var wire 1 $ b $end
$var wire 1 ( carry $end
$var wire 1 & sum $end
$upscope $end
$scope module ha2 $end
$var wire 1 & a $end
$var wire 1 % b $end
$var wire 1 ' carry $end
$var wire 1 ! sum $end
$upscope $end
$upscope $end
$upscope $end
$enddefinitions $end
$comment Show the parameter values. $end
$dumpall
$end
#0
$dumpvars
0(
0'
0&
0%
0$
0#
0"
0!
$end
#2
1!
1%
#4
1&
0%
1$
#6
0&
1%
0$
#8
1"
0!
1'
1&
1$
#10
0"
1!
0'
0%
0$
1#
#12
1"
0!
1'
1%
#14
0'
0&
1(
0%
1$
#16
1'
1&
0(
1%
0$
#18
1!
0'
0&
1(
1$
