FutureWiz_Daily_Verilog_Codes/revision_verilog_codes_july/rev07_tlatch_alrahe/design.v
module t_latch(input clk, rst_n, t, output reg q);
  reg temp;

  always @(clk,rst_n,t) begin
    if (!rst_n)
      temp = 1'b0;
    else if (clk) begin  // latch is transparent when clk is high
      if (t)
        temp = ~temp;
      // else hold
    end
    q = temp;
  end
endmodule

FutureWiz_Daily_Verilog_Codes/revision_verilog_codes_july/rev07_tlatch_alrahe/testbench.v
`timescale 1ns/1ps
module tlatch_test;

  reg t, clk, rst_n;
  wire q;

  // Instantiate DUT
  t_latch dut (
    .clk(clk),
    .rst_n(rst_n),
    .t(t),
    .q(q)
  );

  // Clock generation
  initial begin
    clk = 0;
    forever #5 clk = ~clk; // 10ns clock period
  end

  // Stimulus
  initial begin
    // Initialize inputs
    t = 0;
    rst_n = 0;

    // Apply reset
    #12 rst_n = 1;

    // Toggle T at different clock cycles
    #10 t = 1;  // Expect toggle
    #10 t = 0;  // No toggle
    #10 t = 1;  // Toggle
    #20 t = 0;  // Hold
    #10 t = 1;  // Toggle
    #20 t = 0;

    // Finish simulation
    #40 $finish;
  end

  // Monitor signal values
  initial begin
    $monitor("Time = %0t | rst_n = %b | t = %b | q = %b", $time, rst_n, t, q);
  end

  // Dump waveform
  initial begin
    $dumpfile("wave.vcd");
    $dumpvars(0, tlatch_test);
  end

endmodule

FutureWiz_Daily_Verilog_Codes/revision_verilog_codes_july/rev07_tlatch_alrahe/wave.vcd
$date
	Mon Jul  7 16:20:23 2025
$end
$version
	Icarus Verilog
$end
$timescale
	1ps
$end
$scope module tlatch_test $end
$var wire 1 ! q $end
$var reg 1 " clk $end
$var reg 1 # rst_n $end
$var reg 1 $ t $end
$scope module dut $end
$var wire 1 " clk $end
$var wire 1 # rst_n $end
$var wire 1 $ t $end
$var reg 1 ! q $end
$var reg 1 % temp $end
$upscope $end
$upscope $end
$enddefinitions $end
$comment Show the parameter values. $end
$dumpall
$end
#0
$dumpvars
0%
0$
0#
0"
0!
$end
#5000
1"
#10000
0"
#12000
1#
#15000
1"
#20000
0"
#22000
1$
#25000
1!
1%
1"
#30000
0"
#32000
0$
#35000
1"
#40000
0"
#42000
1$
#45000
0!
0%
1"
#50000
0"
#55000
1!
1%
1"
#60000
0"
#62000
0$
#65000
1"
#70000
0"
#72000
1$
#75000
0!
0%
1"
#80000
0"
#85000
1!
1%
1"
#90000
0"
#92000
0$
