FutureWiz_Daily_Verilog_Codes/revision_verilog_codes_july/rev03_fa_behav/design.v
//full adder using behavioural modelling 
module full_add(a,b,cin,sum,cout);
	input a,b,cin;
	output reg sum,cout;
		
		//to write behavioural code use always block
		always @(a,b,cin) begin
			{cout,sum} = a + b + cin;
			end
endmodule

FutureWiz_Daily_Verilog_Codes/revision_verilog_codes_july/rev02_struct_fa_ha/testbench.v
module fa_struct_test;
	reg a,b,cin;
	wire sum,carry;
	full_add fa1(a,b,cin,sum,cout);
	//generation of the stimulus 
	initial begin
		a = 0; b = 0; cin = 0;
	#2 cin = 1;
	#2 b = 1; cin = 0;
	#2 b = 0; cin = 1;
	#2 b = 1; cin = 1;	
	#2 a = 1; b = 0; cin = 0;
	#2 cin = 1;
	#2 b = 1; cin = 0;
	#2 b = 0; cin = 1;
	#2 b = 1; cin = 1;
	#10; $finish;
	end
	initial begin
	$dumpfile("wave.vcd");
	$dumpvars(0,fa_struct_test);
	end
endmodule

FutureWiz_Daily_Verilog_Codes/revision_verilog_codes_july/rev03_fa_behav/wave.vcd
$date
	Sat Jul  5 15:27:51 2025
$end
$version
	Icarus Verilog
$end
$timescale
	1s
$end
$scope module fa_struct_test $end
$var wire 1 ! sum $end
$var wire 1 " cout $end
$var reg 1 # a $end
$var reg 1 $ b $end
$var reg 1 % cin $end
$scope module fa1 $end
$var wire 1 # a $end
$var wire 1 $ b $end
$var wire 1 % cin $end
$var reg 1 " cout $end
$var reg 1 ! sum $end
$upscope $end
$upscope $end
$enddefinitions $end
$comment Show the parameter values. $end
$dumpall
$end
#0
$dumpvars
0%
0$
0#
0"
0!
$end
#2
1!
1%
#4
0%
1$
#6
1%
0$
#8
1"
0!
1$
#10
0"
1!
0%
0$
1#
#12
1"
0!
1%
#14
0%
1$
#16
1%
0$
#18
1!
1$
