FutureWiz_Daily_Verilog_Codes/revision_verilog_codes_july/rev08_clk_gen_codes/clk_in_diff_ways.v
`timescale 1ns/1ps

module clk_gen_all_methods;

  // Method 1: always block
  reg clk_m1;

  always #5 clk_m1 = ~clk_m1;

  initial begin
    clk_m1 = 0;
  end

  // Method 2: initial + forever
  reg clk_m2;

  initial begin
    clk_m2 = 0;
    forever #10 clk_m2 = ~clk_m2;
  end

  // Method 3: for loop
  reg clk_m3;
  integer i;

  initial begin
    clk_m3 = 0;
    for (i = 0; i < 10; i = i + 1) begin
      #15 clk_m3 = ~clk_m3;
    end
  end

  // Method 4: repeat
  reg clk_m4;

  initial begin
    clk_m4 = 0;
    repeat (10) begin
      #7 clk_m4 = ~clk_m4;
    end
  end

  // Common monitor and simulation control
  initial begin
    $display("Comparing different clock generation methods");
    $monitor("Time=%0t | clk_m1=%b | clk_m2=%b | clk_m3=%b | clk_m4=%b",
             $time, clk_m1, clk_m2, clk_m3, clk_m4);

    $dumpfile("wave.vcd");
    $dumpvars(0, clk_gen_all_methods);

    #200 $finish;  // Enough time to view all clocks
  end

endmodule

FutureWiz_Daily_Verilog_Codes/revision_verilog_codes_july/rev08_clk_gen_codes/wave.vcd
$date
	Mon Jul  7 16:37:59 2025
$end
$version
	Icarus Verilog
$end
$timescale
	1ps
$end
$scope module clk_gen_all_methods $end
$var reg 1 ! clk_m1 $end
$var reg 1 " clk_m2 $end
$var reg 1 # clk_m3 $end
$var reg 1 $ clk_m4 $end
$var integer 32 % i [31:0] $end
$upscope $end
$enddefinitions $end
$comment Show the parameter values. $end
$dumpall
$end
#0
$dumpvars
b0 %
0$
0#
0"
0!
$end
#5000
1!
#7000
1$
#10000
0!
1"
#14000
0$
#15000
1!
b1 %
1#
#20000
0!
0"
#21000
1$
#25000
1!
#28000
0$
#30000
0!
1"
b10 %
0#
#35000
1!
1$
#40000
0!
0"
#42000
0$
#45000
1!
b11 %
1#
#49000
1$
#50000
0!
1"
#55000
1!
#56000
0$
#60000
0!
0"
b100 %
0#
#63000
1$
#65000
1!
#70000
0!
0$
1"
#75000
1!
b101 %
1#
#80000
0!
0"
#85000
1!
#90000
0!
1"
b110 %
0#
#95000
1!
#100000
0!
0"
#105000
1!
b111 %
1#
#110000
0!
1"
#115000
1!
#120000
0!
0"
b1000 %
0#
#125000
1!
#130000
0!
1"
#135000
1!
b1001 %
1#
#140000
0!
0"
#145000
1!
#150000
0!
1"
b1010 %
0#
